{
  "type": "FeatureCollection",
  "features": [
    {
      "type": "Feature",
      "properties": {},
      "geometry": {
        "type": "Polygon",
        "coordinates": [
          [
            [
              24.914073944091793,
              60.17891635180763
            ],
            [
              24.91476058959961,
              60.17490390267368
            ],
            [
              24.915962219238278,
              60.170122472217564
            ],
            [
              24.914245605468746,
              60.16773149599929
            ],
            [
              24.910812377929688,
              60.16764610077336
            ],
            [
              24.906005859375,
              60.16534034577624
            ],
            [
              24.904632568359375,
              60.16311983618494
            ],
            [
              24.904289245605465,
              60.16175329416404
            ],
            [
              24.915103912353516,
              60.162521981042794
            ],
            [
              24.919567108154297,
              60.1623511632902
            ],
            [
              24.921112060546875,
              60.163034428973376
            ],
            [
              24.924545288085938,
              60.16260738958614
            ],
            [
              24.925746917724606,
              60.16183870470511
            ],
            [
              24.933471679687496,
              60.16013045170841
            ],
            [
              24.932613372802734,
              60.157397062225606
            ],
            [
              24.93450164794922,
              60.15474887438931
            ],
            [
              24.94222640991211,
              60.153980005702465
            ],
            [
              24.948577880859375,
              60.15491973165545
            ],
            [
              24.952526092529297,
              60.15568857836394
            ],
            [
              24.956302642822266,
              60.15825127085746
            ],
            [
              24.95716094970703,
              60.16038669531834
            ],
            [
              24.958019256591797,
              60.16226575408094
            ],
            [
              24.95269775390625,
              60.164998738682236
            ],
            [
              24.950294494628906,
              60.16627974697341
            ],
            [
              24.95441436767578,
              60.16892700585851
            ],
            [
              24.958534240722656,
              60.16978091483942
            ],
            [
              24.960937499999996,
              60.17575765630778
            ],
            [
              24.956989288330075,
              60.176184524803276
            ],
            [
              24.95046615600586,
              60.1753307822646
            ],
            [
              24.949779510498047,
              60.17379398977336
            ],
            [
              24.94771957397461,
              60.17251327443952
            ],
            [
              24.942054748535156,
              60.172598657015236
            ],
            [
              24.93844985961914,
              60.17370861030455
            ],
            [
              24.931583404541012,
              60.1759284043717
            ],
            [
              24.928321838378906,
              60.17959927305516
            ],
            [
              24.914073944091793,
              60.17891635180763
            ]
          ]
        ]
      }
    }
  ]
}